cogstream/__init__.py
cogstream/typing.py
cogstream/api/__init__.py
cogstream/api/engines.py
cogstream/api/format.py
cogstream/api/messages.py
cogstream/engine/__init__.py
cogstream/engine/channel.py
cogstream/engine/client.py
cogstream/engine/engine.py
cogstream/engine/io.py
cogstream/engine/srv.py
cogstream/engine/transform.py
cogstream/mediator/__init__.py
cogstream/mediator/client.py
tests/__init__.py
tests/test_channel.py
tests/test_io.py
cogstream_py-0.1.0.dist-info/METADATA
cogstream_py-0.1.0.dist-info/WHEEL
cogstream_py-0.1.0.dist-info/top_level.txt
cogstream_py-0.1.0.dist-info/RECORD
